{
  "getTitle": [
    "Literarni i likovni natječaj naše škole"
  ],
  "getImgs": []
}
{
  "getTitle": [
    "Literarni i likovni natječaj naše škole"
  ],
  "getImgs": []
}
{
  "getTitle": [
    "U PONUDI ZA UPIS U PRVI RAZRED 2023./2024. SLJEDEĆI PROGRAMI:"
  ],
  "getImgs": []
}
{
  "getTitle": [
    "Sastanak predsjednice Vijeća učenika s ravnateljem škole"
  ],
  "getImgs": []
}
{
  "getTitle": [
    "Sastanak predsjednice Vijeća učenika s ravnateljem škole"
  ],
  "getImgs": []
}
{
  "getTitle": [
    "Humanitarna akcija Vijeća učenika"
  ],
  "getImgs": [
    "/upload/ss-tehnicka-ntesla-vu/newsattach/1309/IMG_20221223_124230.jpg",
    "/upload/ss-tehnicka-ntesla-vu/newsattach/1309/IMG_20221223_130927_edit_18730000875266.jpg"
  ]
}
{
  "getTitle": [
    "Humanitarna akcija Vijeća učenika"
  ],
  "getImgs": [
    "/upload/ss-tehnicka-ntesla-vu/newsattach/1309/IMG_20221223_124230.jpg",
    "/upload/ss-tehnicka-ntesla-vu/newsattach/1309/IMG_20221223_130927_edit_18730000875266.jpg"
  ]
}
{
  "getTitle": [
    "Međunarodni dan sjećanja na žrtve Holokausta"
  ],
  "getImgs": []
}
{
  "getTitle": [
    "Proslavljen 87. rođendan naše škole"
  ],
  "getImgs": []
}
{
  "getTitle": [
    "Završni radovi"
  ],
  "getImgs": []
}
{
  "getTitle": [
    "Završni radovi"
  ],
  "getImgs": []
}
{
  "getTitle": [
    "Ekolozi u Tehničkoj školi Nikole Tesle"
  ],
  "getImgs": []
}
{
  "getTitle": [
    "IndexHR o robotici u našoj školi"
  ],
  "getImgs": []
}
{
  "getTitle": [
    "Popis licenciranih obrtnika"
  ],
  "getImgs": [
    "/upload/ss-tehnicka-ntesla-vu/newsattach/1112/Popis_licenciranih_obrtnika.pdf"
  ]
}
{
  "getTitle": [],
  "getImgs": []
}
